moxel/__init__.py
moxel/constants.py
moxel/core.py
moxel/utils.py
moxel/bin/.DS_Store
moxel/bin/.download.sh.swp
moxel/bin/__init__.py
moxel/bin/__init__.pyc
moxel/bin/command_line.py
moxel/bin/command_line.pyc
moxel/bin/download.sh
moxel/bin/linux/moxel
moxel/bin/osx/moxel
moxel/bin/windows/moxel
moxel/space/__init__.py
moxel/space/array.py
moxel/space/core.py
moxel/space/image.py
moxel/space/json.py
moxel/space/string.py
moxel/space/utils.py
moxel-0.0.3.post41.dist-info/DESCRIPTION.rst
moxel-0.0.3.post41.dist-info/METADATA
moxel-0.0.3.post41.dist-info/RECORD
moxel-0.0.3.post41.dist-info/WHEEL
moxel-0.0.3.post41.dist-info/entry_points.txt
moxel-0.0.3.post41.dist-info/metadata.json
moxel-0.0.3.post41.dist-info/top_level.txt
