Metadata-Version: 2.0
Name: moxel
Version: 0.0.3.post41
Summary: Share and discover the world's best models, built by the community.
Home-page: http://moxel.ai
Author: Moxel team
Author-email: support@moxel.ai
License: GPLv3
Keywords: Machine Learning,Model,Deep Learning,Platform
Platform: UNKNOWN
Classifier: Development Status :: 2 - Pre-Alpha
Classifier: Topic :: Scientific/Engineering :: Artificial Intelligence
Classifier: Environment :: Console
Classifier: Programming Language :: Python :: 3
Requires-Dist: moxel-python-driver
Requires-Dist: numpy
Requires-Dist: pillow
Requires-Dist: requests
Requires-Dist: simplejson
Requires-Dist: six
